root_subvol_snapshot/__init__.py
root_subvol_snapshot/py.typed
root_subvol_snapshot-0.1.0.dist-info/LICENSE
root_subvol_snapshot-0.1.0.dist-info/METADATA
root_subvol_snapshot-0.1.0.dist-info/WHEEL
root_subvol_snapshot-0.1.0.dist-info/RECORD
