Metadata-Version: 2.1
Name: root-subvol-snapshot
Version: 0.1.0
Summary: Create snapshots of top-level BtrFS subvolumes
License: GPL v3
Author: Max Görner
Author-email: 5477952+MaxG87@users.noreply.github.com
Requires-Python: >=3.8.1,<3.12
Classifier: License :: Other/Proprietary License
Classifier: Programming Language :: Python :: 3
Classifier: Programming Language :: Python :: 3.9
Classifier: Programming Language :: Python :: 3.10
Classifier: Programming Language :: Python :: 3.11
Requires-Dist: shell-interface (>=0.12.0,<0.13.0)
Requires-Dist: storage-device-managers (>=0.13.0,<0.14.0)
Requires-Dist: typer (>=0.9.0,<0.10.0)
